dattasai12_package/__init__.py
dattasai12_package/your_module.py
palindrome_package-0.1.0.dist-info/METADATA
palindrome_package-0.1.0.dist-info/WHEEL
palindrome_package-0.1.0.dist-info/top_level.txt
palindrome_package-0.1.0.dist-info/RECORD
